{
  "juego_1": {
    "nivel_1": [
      {
        "palabra": "SOL",
        "imagen": "SOL.png",
        "usada": "no"
      },
      {
        "palabra": "MESA",
        "imagen": "MESA.png",
        "usada": "no"
      },
      {
        "palabra": "MANO",
        "imagen": "MANO.png",
        "usada": "no"
      },
      {
        "palabra": "CAMA",
        "imagen": "CAMA.png",
        "usada": "si"
      },
      {
        "palabra": "CASA",
        "imagen": "CASA.png",
        "usada": "si"
      },
      {
        "palabra": "NUBE",
        "imagen": "NUBE.png",
        "usada": "no"
      },
      {
        "palabra": "AUTO",
        "imagen": "AUTO.png",
        "usada": "si"
      },
      {
        "palabra": "TREN",
        "imagen": "TREN.png",
        "usada": "si"
      },
      {
        "palabra": "LUNA",
        "imagen": "LUNA.png",
        "usada": "si"
      },
      {
        "palabra": "MONO",
        "imagen": "MONO.png",
        "usada": "si"
      }
    ],
    "nivel_2": [
      {
        "palabra": "perro",
        "imagen": "PERRO.png",
        "usada": "si"
      },
      {
        "palabra": "silla",
        "imagen": "SILLA.png",
        "usada": "si"
      },
      {
        "palabra": "avión",
        "imagen": "AVION.png",
        "usada": "si"
      },
      {
        "palabra": "árbol",
        "imagen": "ARBOL.png",
        "usada": "si"
      },
      {
        "palabra": "gorro",
        "imagen": "GORRO.png",
        "usada": "si"
      },
      {
        "palabra": "fuego",
        "imagen": "FUEGO.png",
        "usada": "si"
      },
      {
        "palabra": "piano",
        "imagen": "PIANO.png",
        "usada": "si"
      },
      {
        "palabra": "carpa",
        "imagen": "CARPA.png",
        "usada": "si"
      },
      {
        "palabra": "lápiz",
        "imagen": "LAPIZ.png",
        "usada": "si"
      },
      {
        "palabra": "globo",
        "imagen": "GLOBO.png",
        "usada": "si"
      }
    ],
    "nivel_3": [
      {
        "palabra": "remera",
        "imagen": "REMERA.PNG",
        "usada": "si"
      },
      {
        "palabra": "elefante",
        "imagen": "ELEFANTE.png",
        "usada": "no"
      },
      {
        "palabra": "dientes",
        "imagen": "DIENTE.png",
        "usada": "si"
      },
      {
        "palabra": "tijera",
        "imagen": "TIJERA.png",
        "usada": "si"
      },
      {
        "palabra": "tomate",
        "imagen": "TOMATE.png",
        "usada": "si"
      },
      {
        "palabra": "banana",
        "imagen": "BANANA.png",
        "usada": "no"
      },
      {
        "palabra": "lluvia",
        "imagen": "lluvia.png",
        "usada": "no"
      },
      {
        "palabra": "conejo",
        "imagen": "conejo.png",
        "usada": "si"
      },
      {
        "palabra": "pileta",
        "imagen": "PILETA.png",
        "usada": "si"
      },
      {
        "palabra": "helado",
        "imagen": "helado.png",
        "usada": "si"
      }
    ]
  },
  "juego_2": {
    "nivel_1": {
      "usada": "no",
      "grupo_1": {
        "usada": "no",
        "palabras": [
          {
            "palabra": "Azul",
            "imagen": "azul.png"
          },
          {
            "palabra": "Amarillo",
            "imagen": "amarillo.png"
          },
          {
            "palabra": "Naranja",
            "imagen": "naranja.png"
          },
          {
            "palabra": "Rojo",
            "imagen": "rojo.png"
          },
          {
            "palabra": "Violeta",
            "imagen": "violeta.png"
          },
          {
            "palabra": "Verde",
            "imagen": "verde.png"
          }
        ]
      },
      "grupo_2": {
        "usada": "no",
        "palabras": [
          {
            "palabra": "Feliz",
            "imagen": "feliz.png"
          },
          {
            "palabra": "Triste",
            "imagen": "triste.png"
          },
          {
            "palabra": "Miedo",
            "imagen": "miedo.png"
          },
          {
            "palabra": "Enojo",
            "imagen": "enojo.png"
          },
          {
            "palabra": "Desagrado",
            "imagen": "desagrado.png"
          },
          {
            "palabra": "Confusión",
            "imagen": "confusión.png"
          }
        ]
      }
    },
    "nivel_2": {
      "usada": "no",
      "grupo_1": {
        "usada": "no",
        "palabras": [
          {
            "palabra": "Cocodrilo",
            "imagen": "cocodrilo.png"
          },
          {
            "palabra": "Pájaro",
            "imagen": "pajaro.png"
          },
          {
            "palabra": "Ratón",
            "imagen": "raton.png"
          },
          {
            "palabra": "Tortuga",
            "imagen": "tortuga.png"
          },
          {
            "palabra": "Pez",
            "imagen": "pez.png"
          },
          {
            "palabra": "Oso",
            "imagen": "oso.png"
          }
        ]
      },
      "grupo_2": {
        "usada": "no",
        "palabras": [
          {
            "palabra": "Hamburguesa",
            "imagen": "hamburguesa.png"
          },
          {
            "palabra": "Pizza",
            "imagen": "pizza.png"
          },
          {
            "palabra": "Ensalada",
            "imagen": "ensalada.png"
          },
          {
            "palabra": "Fideos",
            "imagen": "fideos.png"
          },
          {
            "palabra": "Milanesa",
            "imagen": "milanesa.png"
          },
          {
            "palabra": "Arroz",
            "imagen": "arroz.png"
          }
        ]
      }
    },
    "nivel_3": {
      "usada": "no",
      "grupo_1": {
        "usada": "no",
        "palabras": [
          {
            "palabra": "Soleado",
            "imagen": "sol.png"
          },
          {
            "palabra": "Arcoiris",
            "imagen": "arcoiris.png"
          },
          {
            "palabra": "Nublado",
            "imagen": "nublado.png"
          },
          {
            "palabra": "Viento",
            "imagen": "viento.png"
          },
          {
            "palabra": "Nieve",
            "imagen": "nieve.png"
          },
          {
            "palabra": "Tormenta",
            "imagen": "tormenta.png"
          }
        ]
      },
      "grupo_2": {
        "usada": "no",
        "palabras": [
          {
            "palabra": "Ojo",
            "imagen": "ojo.png"
          },
          {
            "palabra": "Boca",
            "imagen": "boca.png"
          },
          {
            "palabra": "Nariz",
            "imagen": "nariz.png"
          },
          {
            "palabra": "Mano",
            "imagen": "mano.png"
          },
          {
            "palabra": "Pie",
            "imagen": "pie.png"
          },
          {
            "palabra": "Oreja",
            "imagen": "oreja.png"
          }
        ]
      }
    }
  },
  "juego_3": {
    "nivel_1": {
      "usada": "no",
      "grupo_1": {
        "usada": "si",
        "palabras": [
          {
            "palabra": "Perro",
            "imagen": "url_externa_perro"
          },
          {
            "palabra": "Pato",
            "imagen": "url_externa_pato"
          },
          {
            "palabra": "Conejo",
            "imagen": "url_externa_conejo"
          },
          {
            "palabra": "Oso",
            "imagen": "url_externa_oso"
          }
        ]
      },
      "grupo_2": {
        "usada": "si",
        "palabras": [
          {
            "palabra": "Elefante",
            "imagen": "elefante.png"
          },
          {
            "palabra": "Jirafa",
            "imagen": "jirafa.png"
          },
          {
            "palabra": "Ratón",
            "imagen": "raton.png"
          },
          {
            "palabra": "Tortuga",
            "imagen": "tortuga.png"
          }
        ]
      },
      "grupo_3": {
        "usada": "si",
        "palabras": [
          {
            "palabra": "Medusa",
            "imagen": "url_externa_medusa"
          },
          {
            "palabra": "León",
            "imagen": "url_externa_leon"
          },
          {
            "palabra": "Gato",
            "imagen": "url_externa_gato"
          },
          {
            "palabra": "Cangrejo",
            "imagen": "url_externa_cangrejo"
          }
        ]
      },
      "grupo_4": {
        "usada": "si",
        "palabras": [
          {
            "palabra": "Pez",
            "imagen": "url_externa_pez"
          },
          {
            "palabra": "Pulpo",
            "imagen": "url_externa_pulpo"
          },
          {
            "palabra": "Pájaro",
            "imagen": "url_externa_pajaro"
          },
          {
            "palabra": "Delfín",
            "imagen": "url_externa_delfin"
          }
        ]
      },
      "grupo_5": {
        "usada": "si",
        "palabras": [
          {
            "palabra": "Tiburón",
            "imagen": "url_externa_tiburon"
          },
          {
            "palabra": "Búho",
            "imagen": "url_externa_buho"
          },
          {
            "palabra": "Cocodrilo",
            "imagen": "url_externa_cocodrilo"
          },
          {
            "palabra": "Serpiente",
            "imagen": "url_externa_serpiente"
          }
        ]
      }
    },
    "nivel_2": {
      "usada": "no",
      "grupo_1": {
        "usada": "si",
        "palabras": [
          {
            "palabra": "Banana",
            "imagen": "url_externa_banana"
          },
          {
            "palabra": "Manzana",
            "imagen": "url_externa_manzana"
          },
          {
            "palabra": "Frutilla",
            "imagen": "url_externa_frutilla"
          },
          {
            "palabra": "Sandía",
            "imagen": "url_externa_sandia"
          }
        ]
      },
      "grupo_2": {
        "usada": "si",
        "palabras": [
          {
            "palabra": "Tomate",
            "imagen": "url_externa_tomate"
          },
          {
            "palabra": "Lechuga",
            "imagen": "url_externa_lechuga"
          },
          {
            "palabra": "Zanahoria",
            "imagen": "url_externa_zanahoria"
          },
          {
            "palabra": "Limón",
            "imagen": "url_externa_limom"
          }
        ]
      },
      "grupo_3": {
        "usada": "si",
        "palabras": [
          {
            "palabra": "Cereza",
            "imagen": "url_externa_cereza"
          },
          {
            "palabra": "Kiwi",
            "imagen": "url_externa_kiwi"
          },
          {
            "palabra": "Pera",
            "imagen": "url_externa_pera"
          },
          {
            "palabra": "Durazno",
            "imagen": "url_externa_durazno"
          }
        ]
      },
      "grupo_4": {
        "usada": "si",
        "palabras": [
          {
            "palabra": "Choclo",
            "imagen": "url_externa_choclo"
          },
          {
            "palabra": "Palta",
            "imagen": "url_externa_palta"
          },
          {
            "palabra": "Calabaza",
            "imagen": "url_externa_calabaza"
          },
          {
            "palabra": "Huevo",
            "imagen": "url_externa_huevo"
          }
        ]
      },
      "grupo_5": {
        "usada": "si",
        "palabras": [
          {
            "palabra": "Melón",
            "imagen": "url_externa_melon"
          },
          {
            "palabra": "Naranja",
            "imagen": "url_externa_naranja"
          },
          {
            "palabra": "Coco",
            "imagen": "url_externa_coco"
          },
          {
            "palabra": "Uva",
            "imagen": "url_externa_uva"
          }
        ]
      }
    },
    "nivel_3": {
      "usada": "no",
      "grupo_1": {
        "usada": "si",
        "palabras": [
          {
            "palabra": "Botas",
            "imagen": "BOTAS.png"
          },
          {
            "palabra": "Zapatillas",
            "imagen": "ZAPATILLAS.png"
          },
          {
            "palabra": "Ojotas",
            "imagen": "OJOTAS.png"
          },
          {
            "palabra": "Sandalias",
            "imagen": "SANDALIAS.png"
          }
        ]
      },
      "grupo_2": {
        "usada": "si",
        "palabras": [
          {
            "palabra": "Remera",
            "imagen": "REMERA.png"
          },
          {
            "palabra": "Blusa",
            "imagen": "BLUSA.png"
          },
          {
            "palabra": "Camisa",
            "imagen": "CAMISA.png"
          },
          {
            "palabra": "Musculosa",
            "imagen": "MUSCULOSA.png"
          }
        ]
      },
      "grupo_3": {
        "usada": "si",
        "palabras": [
          {
            "palabra": "Jean",
            "imagen": "JEAN.png"
          },
          {
            "palabra": "Short",
            "imagen": "SHORT.png"
          },
          {
            "palabra": "Pollera",
            "imagen": "POLLERA.png"
          },
          {
            "palabra": "Calza",
            "imagen": "CALZA.PNG"
          }
        ]
      },
      "grupo_4": {
        "usada": "si",
        "palabras": [
          {
            "palabra": "Vestido",
            "imagen": "VESTIDO.png"
          },
          {
            "palabra": "Traje",
            "imagen": "TRAJE,png"
          },
          {
            "palabra": "Corbata",
            "imagen": "CORBATAS.png"
          },
          {
            "palabra": "Joyas",
            "imagen": "JOYAS.png"
          }
        ]
      },
      "grupo_5": {
        "usada": "si",
        "palabras": [
          {
            "palabra": "Campera",
            "imagen": "./CAMPERA.png"
          },
          {
            "palabra": "Buzo",
            "imagen": "./BUZO.png"
          },
          {
            "palabra": "Pijama",
            "imagen": "./PIJAMA.png"
          },
          {
            "palabra": "Medias",
            "imagen": "./MEDIAS.png"
          }
        ]
      }
    }
  }
}